mbed_host_tests/__init__.py
mbed_host_tests/mbedflsh.py
mbed_host_tests/mbedhtrun.py
mbed_host_tests/host_tests/__init__.py
mbed_host_tests/host_tests/base_host_test.py
mbed_host_tests/host_tests/default_auto.py
mbed_host_tests/host_tests/detect_auto.py
mbed_host_tests/host_tests/dev_null_auto.py
mbed_host_tests/host_tests/echo.py
mbed_host_tests/host_tests/hello_auto.py
mbed_host_tests/host_tests/rtc_auto.py
mbed_host_tests/host_tests/wait_us_auto.py
mbed_host_tests/host_tests_conn_proxy/__init__.py
mbed_host_tests/host_tests_conn_proxy/conn_primitive.py
mbed_host_tests/host_tests_conn_proxy/conn_primitive_fastmodel.py
mbed_host_tests/host_tests_conn_proxy/conn_primitive_remote.py
mbed_host_tests/host_tests_conn_proxy/conn_primitive_serial.py
mbed_host_tests/host_tests_conn_proxy/conn_proxy.py
mbed_host_tests/host_tests_logger/__init__.py
mbed_host_tests/host_tests_logger/ht_logger.py
mbed_host_tests/host_tests_plugins/__init__.py
mbed_host_tests/host_tests_plugins/host_test_plugins.py
mbed_host_tests/host_tests_plugins/host_test_registry.py
mbed_host_tests/host_tests_plugins/module_copy_jn51xx.py
mbed_host_tests/host_tests_plugins/module_copy_mbed.py
mbed_host_tests/host_tests_plugins/module_copy_mps2.py
mbed_host_tests/host_tests_plugins/module_copy_pyocd.py
mbed_host_tests/host_tests_plugins/module_copy_shell.py
mbed_host_tests/host_tests_plugins/module_copy_silabs.py
mbed_host_tests/host_tests_plugins/module_copy_stlink.py
mbed_host_tests/host_tests_plugins/module_copy_ublox.py
mbed_host_tests/host_tests_plugins/module_power_cycle_mbed.py
mbed_host_tests/host_tests_plugins/module_reset_jn51xx.py
mbed_host_tests/host_tests_plugins/module_reset_mbed.py
mbed_host_tests/host_tests_plugins/module_reset_mps2.py
mbed_host_tests/host_tests_plugins/module_reset_pyocd.py
mbed_host_tests/host_tests_plugins/module_reset_silabs.py
mbed_host_tests/host_tests_plugins/module_reset_stlink.py
mbed_host_tests/host_tests_plugins/module_reset_ublox.py
mbed_host_tests-1.8.14.dist-info/METADATA
mbed_host_tests-1.8.14.dist-info/WHEEL
mbed_host_tests-1.8.14.dist-info/entry_points.txt
mbed_host_tests-1.8.14.dist-info/top_level.txt
mbed_host_tests-1.8.14.dist-info/RECORD
